subtitle_api/__init__.py
subtitle_api/example.py
subtitle_api-0.0.1.dist-info/LICENCE
subtitle_api-0.0.1.dist-info/METADATA
subtitle_api-0.0.1.dist-info/WHEEL
subtitle_api-0.0.1.dist-info/top_level.txt
subtitle_api-0.0.1.dist-info/RECORD
