Metadata-Version: 2.1
Name: subtitle-api
Version: 0.0.1
Summary: this module provide unofficial subscene.com api for python
Home-page: https://github.com/pypa/sampleproject
Author: Erfan Shekari
Author-email: erfan.dp.co@gmail.com
License: UNKNOWN
Project-URL: Bug Tracker, https://github.com/pypa/sampleproject/issues
Platform: UNKNOWN
Classifier: Programming Language :: Python :: 3
Classifier: License :: OSI Approved :: MIT License
Classifier: Operating System :: OS Independent
Requires-Python: >=3.7
Requires-Dist: IMDbPY (==2021.4.18)
Requires-Dist: beautifulsoup4 (==4.9.0)
Requires-Dist: lxml (==4.6.3)
Requires-Dist: requests (==2.23.0)
